pysysp/__init__.py
pysysp/alpha_lyr_stis_006.fits
pysysp/extinction.py
pysysp/pysysp.py
pysysp/filters/Bessel/B.dat
pysysp/filters/Bessel/I.dat
pysysp/filters/Bessel/R.dat
pysysp/filters/Bessel/U.dat
pysysp/filters/Bessel/V.dat
pysysp/filters/Gaia/G.dat
pysysp-2.0.1.dist-info/METADATA
pysysp-2.0.1.dist-info/WHEEL
pysysp-2.0.1.dist-info/top_level.txt
pysysp-2.0.1.dist-info/RECORD
