Metadata-Version: 2.1
Name: pysysp
Version: 2.0.1
Summary: A package for Synthetic Stellar Photometry
Home-page: https://github.com/mdusilva/pysysp
Author: Manuel Silva
Author-email: madusilva@gmail.com
License: GPLv2
Classifier: Intended Audience :: Developers
Classifier: Intended Audience :: Science/Research
Classifier: License :: OSI Approved :: GNU General Public License (GPL)
Classifier: Operating System :: OS Independent
Classifier: Programming Language :: Python
Classifier: Topic :: Scientific/Engineering :: Astronomy
Requires-Dist: numpy
Requires-Dist: astropy
Requires-Dist: scipy
